{"assets/fonts/Montserrat-Bold.ttf":["assets/fonts/Montserrat-Bold.ttf"],"assets/fonts/Montserrat-Light.ttf":["assets/fonts/Montserrat-Light.ttf"],"assets/fonts/Montserrat-Medium.ttf":["assets/fonts/Montserrat-Medium.ttf"],"assets/fonts/Montserrat-Regular.ttf":["assets/fonts/Montserrat-Regular.ttf"],"assets/fonts/Montserrat-Thin.ttf":["assets/fonts/Montserrat-Thin.ttf"],"assets/images/logo-white.svg":["assets/images/logo-white.svg"],"assets/images/logo.svg":["assets/images/logo.svg"],"assets/images/symbol.svg":["assets/images/symbol.svg"],"packages/cupertino_icons/assets/CupertinoIcons.ttf":["packages/cupertino_icons/assets/CupertinoIcons.ttf"]}